MANIFEST.in
README.md
requirements.txt
setup.cfg
setup.py
cf_buildpack_dashboard/__init__.py
cf_buildpack_dashboard/wsgi.py
cf_buildpack_dashboard.egg-info/PKG-INFO
cf_buildpack_dashboard.egg-info/SOURCES.txt
cf_buildpack_dashboard.egg-info/dependency_links.txt
cf_buildpack_dashboard.egg-info/entry_points.txt
cf_buildpack_dashboard.egg-info/requires.txt
cf_buildpack_dashboard.egg-info/top_level.txt
cf_buildpack_dashboard/api/__init__.py
cf_buildpack_dashboard/api/api.py
cf_buildpack_dashboard/api/run.py
cf_buildpack_dashboard/api/web.py
cf_buildpack_dashboard/api/static/css/bootstrap-grid.css
cf_buildpack_dashboard/api/static/css/bootstrap-grid.css.map
cf_buildpack_dashboard/api/static/css/bootstrap-grid.min.css
cf_buildpack_dashboard/api/static/css/bootstrap-grid.min.css.map
cf_buildpack_dashboard/api/static/css/bootstrap-reboot.css
cf_buildpack_dashboard/api/static/css/bootstrap-reboot.css.map
cf_buildpack_dashboard/api/static/css/bootstrap-reboot.min.css
cf_buildpack_dashboard/api/static/css/bootstrap-reboot.min.css.map
cf_buildpack_dashboard/api/static/css/bootstrap.css
cf_buildpack_dashboard/api/static/css/bootstrap.css.map
cf_buildpack_dashboard/api/static/css/bootstrap.min.css
cf_buildpack_dashboard/api/static/css/bootstrap.min.css.map
cf_buildpack_dashboard/api/static/css/button-open.png
cf_buildpack_dashboard/api/static/css/tree.css
cf_buildpack_dashboard/api/static/js/bootstrap.bundle.js
cf_buildpack_dashboard/api/static/js/bootstrap.bundle.js.map
cf_buildpack_dashboard/api/static/js/bootstrap.bundle.min.js
cf_buildpack_dashboard/api/static/js/bootstrap.bundle.min.js.map
cf_buildpack_dashboard/api/static/js/bootstrap.js
cf_buildpack_dashboard/api/static/js/bootstrap.js.map
cf_buildpack_dashboard/api/static/js/bootstrap.min.js
cf_buildpack_dashboard/api/static/js/bootstrap.min.js.map
cf_buildpack_dashboard/api/static/js/collapsible-list.min.js
cf_buildpack_dashboard/api/static/js/jquery-3.2.1.min.js
cf_buildpack_dashboard/api/static/js/custom/dashboard.js
cf_buildpack_dashboard/api/templates/buildpack.j2.html
cf_buildpack_dashboard/clients/__init__.py
cf_buildpack_dashboard/clients/exceptions.py
cf_buildpack_dashboard/clients/light_api.py
cf_buildpack_dashboard/clients/reply.py
cf_buildpack_dashboard/entities/__init__.py
