Metadata-Version: 1.1
Name: cf-buildpack-dashboard
Version: 0.0.7
Summary: Builpack dashboard for Cloudfoundry
Home-page: UNKNOWN
Author: Claudio Benfatto
Author-email: claudio.benfatto@gmail.com
License: MIT
Keywords: assessment
Platform: UNKNOWN
Classifier: Development Status :: 3 - Alpha
Classifier: Intended Audience :: System Administrators
Classifier: Topic :: System :: Systems Administration
Classifier: License :: OSI Approved :: MIT License
Classifier: Programming Language :: Python :: 3
